ibb_acik_veri_portali/__init__.py
ibb_acik_veri_portali/ispark.py
ibb_acik_veri_portali-0.2.0.dist-info/LICENSE
ibb_acik_veri_portali-0.2.0.dist-info/METADATA
ibb_acik_veri_portali-0.2.0.dist-info/WHEEL
ibb_acik_veri_portali-0.2.0.dist-info/top_level.txt
ibb_acik_veri_portali-0.2.0.dist-info/RECORD
