Metadata-Version: 2.1
Name: ibb_acik_veri_portali
Version: 0.2.0
Summary: Lorem ipsum dolor sit amet.
Author: Arı Bilgi
Author-email: example@example.com
Classifier: Programming Language :: Python :: 3
Classifier: License :: OSI Approved :: MIT License
Classifier: Operating System :: OS Independent
Requires-Python: >=3.6
License-File: LICENSE
Requires-Dist: pandas
Requires-Dist: requests
